th2analytics/__main__.py
th2analytics/forecasting.py
th2analytics-0.0.15.dist-info/LICENSE
th2analytics-0.0.15.dist-info/METADATA
th2analytics-0.0.15.dist-info/WHEEL
th2analytics-0.0.15.dist-info/top_level.txt
th2analytics-0.0.15.dist-info/RECORD
