Metadata-Version: 2.1
Name: th2analytics
Version: 0.0.15
Summary: A Python package for interacting with the thaink2 analytics APIs
Author-email: Farid Azouaou <farid.azouaou@thaink2.com>
Project-URL: Homepage, https://github.com/thaink2/th2analytics_py
Project-URL: Issues, https://github.com/thaink2/th2analytics_py/issues
Classifier: Programming Language :: Python :: 3
Classifier: License :: OSI Approved :: MIT License
Classifier: Operating System :: OS Independent
Requires-Python: >=3.8
License-File: LICENSE
Requires-Dist: requests
Requires-Dist: plotly
